fsm/Problem4_link/slave_fsm.v

module slave_fsm(
    input  wire clk,
    input  wire rst,
    input  wire req,
    input  wire [7:0] data_in,
    output reg  ack,
    output reg  [7:0] last_byte
);

    localparam [1:0]
        S_WAIT_REQ   = 2'd0,
        S_ASSERT_ACK = 2'd1,
        S_HOLD_ACK   = 2'd2,
        S_DROP_ACK   = 2'd3;

    reg [1:0] state, next;
    reg [1:0] hold_cnt;

    always @* begin
        next = state;
        case (state)
            S_WAIT_REQ:   if (req) next = S_ASSERT_ACK;
            S_ASSERT_ACK: next = S_HOLD_ACK;
            S_HOLD_ACK:   if (hold_cnt == 2'd1) next = S_DROP_ACK;
            S_DROP_ACK:   if (!req) next = S_WAIT_REQ;
        endcase
    end

    always @(posedge clk) begin
        if (rst) begin
            state <= S_WAIT_REQ;
            ack <= 0;
            last_byte <= 8'h00;
            hold_cnt <= 0;
        end else begin
            state <= next;
            case (state)
                S_WAIT_REQ: begin
                    ack <= 0;
                end
                S_ASSERT_ACK: begin
                    ack <= 1;
                    last_byte <= data_in; 
                    hold_cnt <= 0;
                end
                S_HOLD_ACK: begin
                    ack <= 1;
                    hold_cnt <= hold_cnt + 1;
                end
                S_DROP_ACK: begin
                    ack <= 0;
                end
            endcase
        end
    end
endmodule

fsm/Problem4_link/master_fsm.v

module master_fsm(
    input  wire clk,
    input  wire rst,
    input  wire ack,
    output reg  req,
    output reg  [7:0] data,
    output reg  done
);

    localparam [2:0]
        M_IDLE      = 3'd0,
        M_REQ       = 3'd1,
        M_WAIT_ACK  = 3'd2,
        M_DROP_REQ  = 3'd3,
        M_FINISH    = 3'd4;

    reg [2:0] state, next;
    reg [1:0] byte_idx; 

    always @* begin
        next = state;
        case (state)
            M_IDLE:     next = M_REQ;
            M_REQ:      next = M_WAIT_ACK;
            M_WAIT_ACK: if (ack) next = M_DROP_REQ;
            M_DROP_REQ: if (!ack) begin
                           if (byte_idx == 2'd3) next = M_FINISH;
                           else next = M_REQ;
                         end
            M_FINISH:   next = M_IDLE;
        endcase
    end
    always @(posedge clk) begin
        if (rst) begin
            state <= M_IDLE;
            byte_idx <= 0;
            req <= 0; data <= 8'h00; done <= 0;
        end else begin
            state <= next;
            done <= 0; 
            case (state)
                M_IDLE: begin
                    req <= 0;
                    byte_idx <= 0;
                end
                M_REQ: begin
                    req <= 1;
                    data <= {6'h0, byte_idx}; 
                end
                M_WAIT_ACK: begin
                    
                end
                M_DROP_REQ: begin
                    req <= 0;
                    if (!ack) byte_idx <= byte_idx + 1;
                end
                M_FINISH: begin
                    done <= 1;
                end
            endcase
        end
    end
endmodule

fsm/Problem4_link/link_top.v

module link_top(
    input  wire clk,
    input  wire rst,
    output wire done
);

    wire req, ack;
    wire [7:0] data;
    wire [7:0] last_byte;

    master_fsm u_master(
        .clk(clk), .rst(rst), .ack(ack),
        .req(req), .data(data), .done(done)
    );

    slave_fsm u_slave(
        .clk(clk), .rst(rst), .req(req),
        .data_in(data), .ack(ack), .last_byte(last_byte)
    );

endmodule

fsm/Problem4_link/tb_link_top.v

`timescale 1ns/1ns

module tb_link_top;

    reg clk, rst;
    wire done;

    link_top dut(.clk(clk), .rst(rst), .done(done));

    initial clk = 0;
    always #5 clk = ~clk;

    initial begin
        $dumpfile("dump.vcd");
        $dumpvars(0, tb_link_top);
    end

    initial begin
        rst = 1;
        repeat (3) @(posedge clk);
        rst = 0;

        wait(done);
        $display("Master asserted done at time %0t", $time);

        repeat (10) @(posedge clk);

        $finish;
    end

    always @(posedge clk) begin
        $strobe("t=%0t req=%b ack=%b data=%h done=%b",
            $time, dut.u_master.req, dut.u_slave.ack, dut.u_master.data, done);
    end

endmodule

fsm/Problem4_link/dump.vcd
$date
	Fri Aug 22 16:53:33 2025
$end
$version
	Icarus Verilog
$end
$timescale
	1ns
$end
$scope module tb_link_top $end
$var wire 1 ! done $end
$var reg 1 " clk $end
$var reg 1 # rst $end
$scope module dut $end
$var wire 1 $ ack $end
$var wire 1 % clk $end
$var wire 8 & data [7:0] $end
$var wire 1 ! done $end
$var wire 8 ' last_byte [7:0] $end
$var wire 1 ( req $end
$var wire 1 ) rst $end
$scope module u_master $end
$var wire 1 $ ack $end
$var wire 1 % clk $end
$var wire 1 ) rst $end
$var reg 2 * byte_idx [1:0] $end
$var reg 8 + data [7:0] $end
$var reg 1 , done $end
$var reg 3 - next [2:0] $end
$var reg 1 . req $end
$var reg 3 / state [2:0] $end
$upscope $end
$scope module u_slave $end
$var wire 1 % clk $end
$var wire 8 0 data_in [7:0] $end
$var wire 1 ( req $end
$var wire 1 ) rst $end
$var reg 1 1 ack $end
$var reg 2 2 hold_cnt [1:0] $end
$var reg 8 3 last_byte [7:0] $end
$var reg 2 4 next [1:0] $end
$var reg 2 5 state [1:0] $end
$upscope $end
$upscope $end
$upscope $end
$enddefinitions $end
#0
$dumpvars
bx 5
bx 4
bx 3
bx 2
x1
bx 0
bx /
x.
bx -
x,
bx +
bx *
1)
x(
bx '
bx &
0%
x$
1#
0"
x!
$end
#5
b1 -
b0 4
0,
0!
b0 +
b0 &
b0 0
0.
0(
b0 *
b0 /
b0 2
b0 3
b0 '
01
0$
b0 5
1"
1%
#10
0"
0%
#15
1"
1%
#20
0"
0%
#25
b10 -
b1 /
0#
0)
1"
1%
#30
0"
0%
#35
b1 4
1.
1(
b10 /
1"
1%
#40
0"
0%
#45
b10 4
b1 5
1"
1%
#50
0"
0%
#55
b11 -
11
1$
b10 5
1"
1%
#60
0"
0%
#65
b11 4
b11 /
b1 2
1"
1%
#70
0"
0%
#75
b0 4
b10 2
b11 5
0.
0(
1"
1%
#80
0"
0%
#85
b1 -
01
0$
b0 5
1"
1%
#90
0"
0%
#95
b10 -
b1 *
b1 /
1"
1%
#100
0"
0%
#105
b1 4
b1 +
b1 &
b1 0
1.
1(
b10 /
1"
1%
#110
0"
0%
#115
b10 4
b1 5
1"
1%
#120
0"
0%
#125
b11 -
b0 2
b1 3
b1 '
11
1$
b10 5
1"
1%
#130
0"
0%
#135
b11 4
b1 2
b11 /
1"
1%
#140
0"
0%
#145
b0 4
0.
0(
b10 2
b11 5
1"
1%
#150
0"
0%
#155
b1 -
01
0$
b0 5
1"
1%
#160
0"
0%
#165
b10 -
b10 *
b1 /
1"
1%
#170
0"
0%
#175
b1 4
b10 +
b10 &
b10 0
1.
1(
b10 /
1"
1%
#180
0"
0%
#185
b10 4
b1 5
1"
1%
#190
0"
0%
#195
b11 -
b0 2
b10 3
b10 '
11
1$
b10 5
1"
1%
#200
0"
0%
#205
b11 4
b11 /
b1 2
1"
1%
#210
0"
0%
#215
b0 4
b10 2
b11 5
0.
0(
1"
1%
#220
0"
0%
#225
b1 -
01
0$
b0 5
1"
1%
#230
0"
0%
#235
b10 -
b11 *
b1 /
1"
1%
#240
0"
0%
#245
b1 4
b11 +
b11 &
b11 0
1.
1(
b10 /
1"
1%
#250
0"
0%
#255
b10 4
b1 5
1"
1%
#260
0"
0%
#265
b11 -
b0 2
b11 3
b11 '
11
1$
b10 5
1"
1%
#270
0"
0%
#275
b11 4
b1 2
b11 /
1"
1%
#280
0"
0%
#285
b0 4
0.
0(
b10 2
b11 5
1"
1%
#290
0"
0%
#295
b100 -
01
0$
b0 5
1"
1%
#300
0"
0%
#305
b0 -
b0 *
b100 /
1"
1%
#310
0"
0%
#315
b1 -
1,
1!
b0 /
1"
1%
#320
0"
0%
#325
b10 -
0,
0!
b1 /
1"
1%
#330
0"
0%
#335
b1 4
b0 +
b0 &
b0 0
1.
1(
b10 /
1"
1%
#340
0"
0%
#345
b10 4
b1 5
1"
1%
#350
0"
0%
#355
b11 -
b0 2
b0 3
b0 '
11
1$
b10 5
1"
1%
#360
0"
0%
#365
b11 4
b11 /
b1 2
1"
1%
#370
0"
0%
#375
b0 4
b10 2
b11 5
0.
0(
1"
1%
#380
0"
0%
#385
b1 -
01
0$
b0 5
1"
1%
#390
0"
0%
#395
b10 -
b1 *
b1 /
1"
1%
#400
0"
0%
#405
b1 4
b1 +
b1 &
b1 0
1.
1(
b10 /
1"
1%
#410
0"
0%
#415
b10 4
b1 5
1"
1%
