fsm/Problem3_vending/vending_mealy.v

module vending_mealy(
    input  wire       clk,
    input  wire       rst,    
    input  wire [1:0] coin,   
    output wire       dispense, 
    output wire       chg5      
);

    localparam [1:0] S0  = 2'b00;
    localparam [1:0] S5  = 2'b01;
    localparam [1:0] S10 = 2'b10;
    localparam [1:0] S15 = 2'b11;

    reg [1:0] state, next_state;

    wire [4:0] coin_val;
    assign coin_val = (coin == 2'b01) ? 5 :
                      (coin == 2'b10) ? 10 : 0;

    reg [4:0] total_val;
    always @(*) begin
        case (state)
            S0:  total_val = 0;
            S5:  total_val = 5;
            S10: total_val = 10;
            S15: total_val = 15;
            default: total_val = 0;
        endcase
    end

    wire [5:0] new_total = total_val + coin_val; 
    assign dispense = (coin_val != 0) && (new_total >= 20);
    assign chg5    = (coin_val != 0) && (new_total == 25);

    always @(*) begin
    
        next_state = state;

        if (coin_val == 0) begin
           
            next_state = state;
        end else begin
           
            if (new_total >= 20) begin
                
                next_state = S0;
            end else begin
                
                case (new_total)
                    0:  next_state = S0;
                    5:  next_state = S5;
                    10: next_state = S10;
                    15: next_state = S15;
                    default: next_state = S0;
                endcase
            end
        end
    end

    always @(posedge clk) begin
        if (rst) begin
            state <= S0;
        end else begin
            state <= next_state;
        end
    end

endmodule

fsm/Problem3_vending/tb_vending_mealy.v
`timescale 1ns/1ns

module tb_vending_mealy;

    reg clk, rst;
    reg [1:0] coin;
    wire dispense, chg5;

    vending_mealy dut(
        .clk(clk), .rst(rst), .coin(coin),
        .dispense(dispense), .chg5(chg5)
    );

    initial clk = 0;
    always #5 clk = ~clk;

    initial begin
        $dumpfile("dump.vcd");
        $dumpvars(0, tb_vending_mealy);
    end

    task put_coin;
        input [1:0] c;          
        input exp_disp;        
        input exp_chg;          
        begin
            @(negedge clk);
            coin = c;
            @(posedge clk);  
            if (dispense !== exp_disp)
                $display("ERROR: coin=%b exp_disp=%b got=%b", c, exp_disp, dispense);
            if (chg5 !== exp_chg)
                $display("ERROR: coin=%b exp_chg=%b got=%b", c, exp_chg, chg5);
            @(negedge clk);
            coin = 2'b00; 
        end
    endtask

    task idle;
        begin
            @(negedge clk);
            coin = 2'b00;
            @(posedge clk);
            if (dispense) $display("ERROR: idle -> dispense=1");
            if (chg5)     $display("ERROR: idle -> chg5=1");
        end
    endtask

    initial begin
        rst = 1; coin = 2'b00;
        repeat (2) @(posedge clk);
        rst = 0;

        $display("Test1: 10 + 10 => vend");
        put_coin(2'b10, 0, 0); 
                put_coin(2'b10, 1, 0); 
        idle();

        $display("Test2: 5 + 5 + 10 => vend");
        put_coin(2'b01, 0, 0); 
        put_coin(2'b01, 0, 0); 
        put_coin(2'b10, 1, 0); 

        idle();

        $display("Test3: 10 + 5 + 10 => vend + change");
        put_coin(2'b10, 0, 0); 
        put_coin(2'b01, 0, 0); 
        put_coin(2'b10, 1, 1); 

        idle();

        $display("Test4: invalid coin (11) ignored");
        put_coin(2'b11, 0, 0); 

        idle();

        $display("Simulation finished.");
        $finish;
    end

endmodule

fsm/Problem3_vending/dump.vcd
$date
	Fri Aug 22 16:41:36 2025
$end
$version
	Icarus Verilog
$end
$timescale
	1ns
$end
$scope module tb_vending_mealy $end
$var wire 1 ! chg5 $end
$var wire 1 " dispense $end
$var reg 1 # clk $end
$var reg 2 $ coin [1:0] $end
$var reg 1 % rst $end
$scope module dut $end
$var wire 1 ! chg5 $end
$var wire 1 & clk $end
$var wire 2 ' coin [1:0] $end
$var wire 5 ( coin_val [4:0] $end
$var wire 1 " dispense $end
$var wire 6 ) new_total [5:0] $end
$var wire 1 * rst $end
$var reg 2 + next_state [1:0] $end
$var reg 2 , state [1:0] $end
$var reg 5 - total_val [4:0] $end
$upscope $end
$scope task idle $end
$upscope $end
$scope task put_coin $end
$var reg 2 . c [1:0] $end
$var reg 1 / exp_chg $end
$var reg 1 0 exp_disp $end
$upscope $end
$upscope $end
$enddefinitions $end
#0
$dumpvars
x0
x/
bx .
bx -
bx ,
bx +
1*
bx )
b0 (
b0 '
0&
1%
b0 $
0#
0"
0!
$end
#5
b0 +
b0 -
b0 )
b0 ,
1#
1&
#10
0#
0&
#15
0/
00
b10 .
0%
0*
1#
1&
#20
b10 +
b1010 )
b1010 (
b10 $
b10 '
0#
0&
#25
1"
b0 +
b1010 -
b10100 )
b10 ,
1#
1&
#30
0"
b10 +
b1010 )
b0 (
10
b0 $
b0 '
0#
0&
#35
1#
1&
#40
1"
b0 +
b10100 )
b1010 (
b10 $
b10 '
0#
0&
#45
0"
b10 +
b0 -
b1010 )
b0 ,
1#
1&
#50
b0 +
b0 )
b0 (
b0 $
b0 '
0#
0&
#55
1#
1&
#60
0#
0&
#65
00
b1 .
1#
1&
#70
b1 +
b101 )
b101 (
b1 $
b1 '
0#
0&
#75
b10 +
b101 -
b1010 )
b1 ,
1#
1&
#80
b1 +
b101 )
b0 (
b0 $
b0 '
0#
0&
#85
1#
1&
#90
b10 +
b1010 )
b101 (
b1 $
b1 '
0#
0&
#95
b11 +
b1010 -
b1111 )
b10 ,
1#
1&
#100
b10 +
b1010 )
b0 (
10
b10 .
b0 $
b0 '
0#
0&
#105
1#
1&
#110
1"
b0 +
b10100 )
b1010 (
b10 $
b10 '
0#
0&
#115
0"
b10 +
b0 -
b1010 )
b0 ,
1#
1&
#120
b0 +
b0 )
b0 (
b0 $
b0 '
0#
0&
#125
1#
1&
#130
0#
0&
#135
00
1#
1&
#140
b10 +
b1010 )
b1010 (
b10 $
b10 '
0#
0&
#145
1"
b0 +
b1010 -
b10100 )
b10 ,
1#
1&
#150
0"
b10 +
b1010 )
b0 (
b1 .
b0 $
b0 '
0#
0&
#155
1#
1&
#160
b11 +
b1111 )
b101 (
b1 $
b1 '
0#
0&
#165
1"
b0 +
b1111 -
b10100 )
b11 ,
1#
1&
#170
0"
b11 +
b1111 )
b0 (
1/
10
b10 .
b0 $
b0 '
0#
0&
#175
1#
1&
#180
1"
1!
b0 +
b11001 )
b1010 (
b10 $
b10 '
0#
0&
#185
0"
0!
b10 +
b0 -
b1010 )
b0 ,
1#
1&
#190
b0 +
b0 )
b0 (
b0 $
b0 '
0#
0&
#195
1#
1&
#200
0#
0&
#205
0/
00
b11 .
1#
1&
#210
b11 $
b11 '
0#
0&
#215
1#
1&
#220
b0 $
b0 '
0#
0&
